Cargo.toml
MANIFEST.in
README.md
pyproject.toml
setup.py
isync/__init__.py
isync.egg-info/PKG-INFO
isync.egg-info/SOURCES.txt
isync.egg-info/dependency_links.txt
isync.egg-info/not-zip-safe
isync.egg-info/requires.txt
isync.egg-info/top_level.txt
src/lib.rs