Metadata-Version: 2.1
Name: isync
Version: 0.0.0
Summary: .
Home-page: https://github.com/lycantropos/isync/
Download-URL: https://github.com/lycantropos/isync/archive/master.zip
Author-email: Azat Ibrakov <azatibrakov@gmail.com>
Classifier: License :: OSI Approved :: MIT License
Classifier: Programming Language :: Python :: 3.9
Classifier: Programming Language :: Python :: 3.10
Classifier: Programming Language :: Python :: 3.11
Classifier: Programming Language :: Python :: 3.12
Classifier: Programming Language :: Python :: Implementation :: CPython
Classifier: Programming Language :: Python :: Implementation :: PyPy
Classifier: Programming Language :: Python :: Implementation :: CPython
Classifier: Programming Language :: Python :: Implementation :: PyPy
Requires-Python: >=3.9
Provides-Extra: tests
Requires-Dist: hypothesis<7.0,>=6.88.3; extra == "tests"
Requires-Dist: pytest<8.0,>=7.4.3; extra == "tests"
